json2db/ModelFactory.py
json2db/__init__.py
json2db/config.py
json2db/converter.py
json2db/core.py
json2db/types.py
json2db-3.2.3.dist-info/LICENSE
json2db-3.2.3.dist-info/METADATA
json2db-3.2.3.dist-info/WHEEL
json2db-3.2.3.dist-info/top_level.txt
json2db-3.2.3.dist-info/RECORD
