Metadata-Version: 2.1
Name: json2db
Version: 3.2.3
Summary: convert json to relational db
Home-page: https://github.com/mrzhangboss/json2db
Author: mrzhangboss
Author-email: 2529450174@qq.com
License: UNKNOWN
Platform: UNKNOWN
Classifier: Programming Language :: Python :: 3
Classifier: License :: OSI Approved :: MIT License
Classifier: Operating System :: OS Independent
Requires-Python: >=3.6.0
Requires-Dist: sqlalchemy
Requires-Dist: attrs
Requires-Dist: python-dateutil
